d0da/cli.py
d0da/d0da_feature.py
d0da/d0da_report.proto
d0da/d0da_report.py
d0da/d0da_report_pb2.py
d0da/device_linux.py
d0da/helper.py
d0da/hidraw.py
d0da-0.10.0.dist-info/METADATA
d0da-0.10.0.dist-info/WHEEL
d0da-0.10.0.dist-info/entry_points.txt
d0da-0.10.0.dist-info/RECORD
