Metadata-Version: 2.3
Name: d0da
Version: 0.10.0
Summary: Wooting D0DA protocol
License: GPL-3.0
Author: Dick Marinus
Requires-Python: >=3.11,<4.0
Classifier: License :: OSI Approved :: GNU General Public License v3 (GPLv3)
Classifier: Programming Language :: Python :: 3
Classifier: Programming Language :: Python :: 3.11
Classifier: Programming Language :: Python :: 3.12
Classifier: Programming Language :: Python :: 3.13
Provides-Extra: linux
Requires-Dist: click (>=8.1.3,<9.0.0)
Requires-Dist: ioctl-opt (>=1.3,<2.0) ; extra == "linux"
Requires-Dist: protobuf (>3.19)
Requires-Dist: pyudev (>=0.24.1,<0.25.0) ; extra == "linux"
